morpheus/__init__.py
morpheus/api.py
morpheus/cli/__init__.py
morpheus/cli/main.py
morpheus/cli/utils.py
morpheus/cli/commands/__init__.py
morpheus/cli/commands/create.py
morpheus/cli/commands/dag.py
morpheus/cli/commands/downgrade.py
morpheus/cli/commands/init.py
morpheus/cli/commands/status.py
morpheus/cli/commands/upgrade.py
morpheus/config/__init__.py
morpheus/config/config.py
morpheus/core/__init__.py
morpheus/core/dag_resolver.py
morpheus/core/database_error_handler.py
morpheus/core/executor.py
morpheus/core/operations.py
morpheus/core/validation.py
morpheus/errors/__init__.py
morpheus/errors/base.py
morpheus/errors/documentation.py
morpheus/errors/exception_utils.py
morpheus/errors/migration_errors.py
morpheus/models/__init__.py
morpheus/models/migration.py
morpheus/models/migration_status.py
morpheus/models/priority.py
morpheus/templates/migration.mako
morpheus/validation/__init__.py
morpheus_neo4j-0.4.1.dist-info/METADATA
morpheus_neo4j-0.4.1.dist-info/WHEEL
morpheus_neo4j-0.4.1.dist-info/entry_points.txt
morpheus_neo4j-0.4.1.dist-info/licenses/LICENSE
morpheus_neo4j-0.4.1.dist-info/RECORD
