Metadata-Version: 2.4
Name: morpheus-neo4j
Version: 0.4.1
Summary: DAG-based migration tool for Neo4j databases
Author-email: Fedir Skitsko <fed@azx.io>
License-File: LICENSE
Classifier: Development Status :: 3 - Alpha
Classifier: Intended Audience :: Developers
Classifier: Programming Language :: Python :: 3
Classifier: Programming Language :: Python :: 3.12
Requires-Python: >=3.12
Requires-Dist: click>=8.1.0
Requires-Dist: mako>=1.3.0
Requires-Dist: neo4j>=5.0.0
Requires-Dist: networkx>=3.0
Requires-Dist: omegaconf>=2.3.0
Requires-Dist: pyyaml>=6.0
Requires-Dist: rich>=13.0.0
Provides-Extra: dev
Requires-Dist: pytest-asyncio>=0.21.0; extra == 'dev'
Requires-Dist: pytest-cov>=6.2.1; extra == 'dev'
Requires-Dist: pytest-mock>=3.10.0; extra == 'dev'
Requires-Dist: pytest>=7.0.0; extra == 'dev'
Requires-Dist: ruff>=0.1.0; extra == 'dev'
Requires-Dist: ty; extra == 'dev'
